{
  "updated": "2026-06-23T18:19:34.906355+00:00",
  "source": "Yahoo Finance via yfinance (free/no API key)",
  "cost": "No paid API/service used",
  "quotes": {
    "TXN": {
      "price": 301.95,
      "change": -29.05,
      "change_pct": -8.78,
      "prev_close": 331.0,
      "high_52w": 334.03,
      "low_52w": 152.73,
      "market_cap_bn": 274.8,
      "volume": 4310327
    },
    "ON": {
      "price": 117.63,
      "change": -13.62,
      "change_pct": -10.38,
      "prev_close": 131.25,
      "high_52w": 134.92,
      "low_52w": 44.56,
      "market_cap_bn": 45.73,
      "volume": 5832267
    },
    "MCHP": {
      "price": 93.25,
      "change": -9.13,
      "change_pct": -8.92,
      "prev_close": 102.38,
      "high_52w": 105.91,
      "low_52w": 48.52,
      "market_cap_bn": 50.55,
      "volume": 6138850
    },
    "IFX.DE": {
      "price": 80.56,
      "change": -5.38,
      "change_pct": -6.26,
      "prev_close": 85.94,
      "high_52w": 88.83,
      "low_52w": 30.82,
      "market_cap_bn": 104.69,
      "volume": 4912359
    },
    "ALGM": {
      "price": 56.32,
      "change": -4.9,
      "change_pct": -8.0,
      "prev_close": 61.22,
      "high_52w": 61.67,
      "low_52w": 22.41,
      "market_cap_bn": 10.49,
      "volume": 1886761
    },
    "RRX": {
      "price": 219.65,
      "change": -11.35,
      "change_pct": -4.91,
      "prev_close": 231.0,
      "high_52w": 236.35,
      "low_52w": 127.96,
      "market_cap_bn": 14.62,
      "volume": 558005
    },
    "6324.T": {
      "price": 7700.0,
      "change": -970.0,
      "change_pct": -11.19,
      "prev_close": 8670.0,
      "high_52w": 8870.0,
      "low_52w": 2316.0,
      "market_cap_bn": 728.93,
      "volume": 2282200
    },
    "6268.T": {
      "price": 5152.0,
      "change": -566.0,
      "change_pct": -9.9,
      "prev_close": 5718.0,
      "high_52w": 6113.0,
      "low_52w": 2521.0,
      "market_cap_bn": 603.73,
      "volume": 1539400
    },
    "6481.T": {
      "price": 7882.0,
      "change": -342.0,
      "change_pct": -4.16,
      "prev_close": 8224.0,
      "high_52w": 8244.0,
      "low_52w": 3761.0,
      "market_cap_bn": 883.37,
      "volume": 1026800
    },
    "6861.T": {
      "price": 75680.0,
      "change": -2580.0,
      "change_pct": -3.3,
      "prev_close": 78260.0,
      "high_52w": 84170.0,
      "low_52w": 51510.0,
      "market_cap_bn": 18354.3,
      "volume": 531300
    },
    "6954.T": {
      "price": 7459.0,
      "change": -504.0,
      "change_pct": -6.33,
      "prev_close": 7963.0,
      "high_52w": 8880.0,
      "low_52w": 3699.0,
      "market_cap_bn": 6960.43,
      "volume": 7283200
    },
    "6506.T": {
      "price": 7156.0,
      "change": -539.0,
      "change_pct": -7.0,
      "prev_close": 7695.0,
      "high_52w": 7915.0,
      "low_52w": 2807.0,
      "market_cap_bn": 1856.04,
      "volume": 5160000
    },
    "ABBN.SW": {
      "price": 86.1,
      "change": -2.36,
      "change_pct": -2.67,
      "prev_close": 88.46,
      "high_52w": 89.14,
      "low_52w": 45.29,
      "market_cap_bn": 156.27,
      "volume": 2514892
    },
    "3037.TW": {
      "price": 974.0,
      "change": -31.0,
      "change_pct": -3.08,
      "prev_close": 1005.0,
      "high_52w": 1130.0,
      "low_52w": 110.5,
      "market_cap_bn": 1533.22,
      "volume": 25057448
    }
  }
}